bmrcli/__init__.py
bmrcli-1.1.4.dist-info/LICENSE
bmrcli-1.1.4.dist-info/METADATA
bmrcli-1.1.4.dist-info/WHEEL
bmrcli-1.1.4.dist-info/entry_points.txt
bmrcli-1.1.4.dist-info/top_level.txt
bmrcli-1.1.4.dist-info/RECORD
